{
  "annotations": {
    "list": [
      {
        "builtIn": 1,
        "datasource": "-- Grafana --",
        "enable": true,
        "hide": true,
        "iconColor": "rgba(0, 211, 255, 1)",
        "name": "Annotations & Alerts",
        "type": "dashboard"
      }
    ]
  },
  "editable": false,
  "gnetId": null,
  "graphTooltip": 0,
  "id": 13,
  "iteration": 1589186875267,
  "links": [],
  "panels": [
    {
      "collapsed": false,
      "datasource": null,
      "gridPos": {
        "h": 1,
        "w": 24,
        "x": 0,
        "y": 0
      },
      "id": 17,
      "panels": [],
      "repeat": null,
      "title": "Group Compaction",
      "type": "row"
    },
    {
      "aliasColors": {},
      "bars": false,
      "dashLength": 10,
      "dashes": false,
      "datasource": "$datasource",
      "description": "Shows rate of execution for compactions against blocks that are stored in the bucket by compaction group.",
      "fill": 10,
      "fillGradient": 0,
      "gridPos": {
        "h": 7,
        "w": 12,
        "x": 0,
        "y": 1
      },
      "hiddenSeries": false,
      "id": 1,
      "legend": {
        "avg": false,
        "current": false,
        "max": false,
        "min": false,
        "show": true,
        "total": false,
        "values": false
      },
      "lines": true,
      "linewidth": 0,
      "links": [],
      "nullPointMode": "null as zero",
      "options": {
        "dataLinks": []
      },
      "percentage": false,
      "pointradius": 5,
      "points": false,
      "renderer": "flot",
      "seriesOverrides": [],
      "spaceLength": 10,
      "stack": true,
      "steppedLine": false,
      "targets": [
        {
          "expr": "sum(rate(thanos_compact_group_compactions_total{namespace=\"$namespace\",job=~\"$job\"}[$interval])) by (job, group)",
          "format": "time_series",
          "interval": "",
          "intervalFactor": 2,
          "legendFormat": "compaction {{group}}",
          "legendLink": null,
          "refId": "A",
          "step": 10
        }
      ],
      "thresholds": [],
      "timeFrom": null,
      "timeRegions": [],
      "timeShift": null,
      "title": "Rate",
      "tooltip": {
        "shared": false,
        "sort": 0,
        "value_type": "individual"
      },
      "type": "graph",
      "xaxis": {
        "buckets": null,
        "mode": "time",
        "name": null,
        "show": true,
        "values": []
      },
      "yaxes": [
        {
          "format": "short",
          "label": null,
          "logBase": 1,
          "max": null,
          "min": 0,
          "show": true
        },
        {
          "format": "short",
          "label": null,
          "logBase": 1,
          "max": null,
          "min": null,
          "show": false
        }
      ],
      "yaxis": {
        "align": false,
        "alignLevel": null
      }
    },
    {
      "aliasColors": {
        "error": "#E24D42"
      },
      "bars": false,
      "dashLength": 10,
      "dashes": false,
      "datasource": "$datasource",
      "description": "Shows ratio of errors compared to the total number of executed compactions against blocks that are stored in the bucket.",
      "fill": 10,
      "fillGradient": 0,
      "gridPos": {
        "h": 7,
        "w": 12,
        "x": 12,
        "y": 1
      },
      "hiddenSeries": false,
      "id": 2,
      "legend": {
        "avg": false,
        "current": false,
        "max": false,
        "min": false,
        "show": true,
        "total": false,
        "values": false
      },
      "lines": true,
      "linewidth": 0,
      "links": [],
      "nullPointMode": "null as zero",
      "options": {
        "dataLinks": []
      },
      "percentage": false,
      "pointradius": 5,
      "points": false,
      "renderer": "flot",
      "seriesOverrides": [],
      "spaceLength": 10,
      "stack": true,
      "steppedLine": false,
      "targets": [
        {
          "expr": "sum(rate(thanos_compact_group_compactions_failures_total{namespace=\"$namespace\",job=~\"$job\"}[$interval])) / sum(rate(thanos_compact_group_compactions_total{namespace=\"$namespace\",job=~\"$job\"}[$interval]))",
          "format": "time_series",
          "interval": "",
          "intervalFactor": 2,
          "legendFormat": "error",
          "refId": "A",
          "step": 10
        }
      ],
      "thresholds": [],
      "timeFrom": null,
      "timeRegions": [],
      "timeShift": null,
      "title": "Errors",
      "tooltip": {
        "shared": false,
        "sort": 0,
        "value_type": "individual"
      },
      "type": "graph",
      "xaxis": {
        "buckets": null,
        "mode": "time",
        "name": null,
        "show": true,
        "values": []
      },
      "yaxes": [
        {
          "format": "percentunit",
          "label": null,
          "logBase": 1,
          "max": null,
          "min": 0,
          "show": true
        },
        {
          "format": "short",
          "label": null,
          "logBase": 1,
          "max": null,
          "min": null,
          "show": false
        }
      ],
      "yaxis": {
        "align": false,
        "alignLevel": null
      }
    },
    {
      "collapsed": false,
      "datasource": null,
      "gridPos": {
        "h": 1,
        "w": 24,
        "x": 0,
        "y": 8
      },
      "id": 18,
      "panels": [],
      "repeat": null,
      "title": "Downsample",
      "type": "row"
    },
    {
      "aliasColors": {},
      "bars": false,
      "dashLength": 10,
      "dashes": false,
      "datasource": "$datasource",
      "description": "Shows rate of execution for downsampling against blocks that are stored in the bucket by compaction group.",
      "fill": 10,
      "fillGradient": 0,
      "gridPos": {
        "h": 7,
        "w": 12,
        "x": 0,
        "y": 9
      },
      "hiddenSeries": false,
      "id": 3,
      "legend": {
        "avg": false,
        "current": false,
        "max": false,
        "min": false,
        "show": true,
        "total": false,
        "values": false
      },
      "lines": true,
      "linewidth": 0,
      "links": [],
      "nullPointMode": "null as zero",
      "options": {
        "dataLinks": []
      },
      "percentage": false,
      "pointradius": 5,
      "points": false,
      "renderer": "flot",
      "seriesOverrides": [],
      "spaceLength": 10,
      "stack": true,
      "steppedLine": false,
      "targets": [
        {
          "expr": "sum(rate(thanos_compact_downsample_total{namespace=\"$namespace\",job=~\"$job\",pod=~\"$pod\"}[$interval])) by (group)",
          "format": "time_series",
          "interval": "",
          "intervalFactor": 2,
          "legendFormat": "downsample - {{group}}",
          "legendLink": null,
          "refId": "A",
          "step": 10
        }
      ],
      "thresholds": [],
      "timeFrom": null,
      "timeRegions": [],
      "timeShift": null,
      "title": "Rate",
      "tooltip": {
        "shared": true,
        "sort": 2,
        "value_type": "individual"
      },
      "type": "graph",
      "xaxis": {
        "buckets": null,
        "mode": "time",
        "name": null,
        "show": true,
        "values": []
      },
      "yaxes": [
        {
          "format": "short",
          "label": null,
          "logBase": 1,
          "max": null,
          "min": 0,
          "show": true
        },
        {
          "format": "short",
          "label": null,
          "logBase": 1,
          "max": null,
          "min": null,
          "show": false
        }
      ],
      "yaxis": {
        "align": false,
        "alignLevel": null
      }
    },
    {
      "aliasColors": {
        "error": "#E24D42"
      },
      "bars": false,
      "dashLength": 10,
      "dashes": false,
      "datasource": "$datasource",
      "description": "Shows ratio of errors compared to the total number of executed downsampling against blocks that are stored in the bucket.",
      "fill": 10,
      "fillGradient": 0,
      "gridPos": {
        "h": 7,
        "w": 12,
        "x": 12,
        "y": 9
      },
      "hiddenSeries": false,
      "id": 4,
      "legend": {
        "avg": false,
        "current": false,
        "max": false,
        "min": false,
        "show": true,
        "total": false,
        "values": false
      },
      "lines": true,
      "linewidth": 0,
      "links": [],
      "nullPointMode": "null as zero",
      "options": {
        "dataLinks": []
      },
      "percentage": false,
      "pointradius": 5,
      "points": false,
      "renderer": "flot",
      "seriesOverrides": [],
      "spaceLength": 10,
      "stack": true,
      "steppedLine": false,
      "targets": [
        {
          "expr": "sum(rate(thanos_compact_downsample_failures_total{namespace=\"$namespace\",job=~\"$job\",pod=~\"$pod\"}[$interval])) / sum(rate(thanos_compact_downsample_total{namespace=\"$namespace\",job=~\"$job\",pod=~\"$pod\"}[$interval]))",
          "format": "time_series",
          "interval": "",
          "intervalFactor": 2,
          "legendFormat": "error",
          "refId": "A",
          "step": 10
        }
      ],
      "thresholds": [],
      "timeFrom": null,
      "timeRegions": [],
      "timeShift": null,
      "title": "Errors",
      "tooltip": {
        "shared": false,
        "sort": 0,
        "value_type": "individual"
      },
      "type": "graph",
      "xaxis": {
        "buckets": null,
        "mode": "time",
        "name": null,
        "show": true,
        "values": []
      },
      "yaxes": [
        {
          "format": "percentunit",
          "label": null,
          "logBase": 1,
          "max": null,
          "min": 0,
          "show": true
        },
        {
          "format": "short",
          "label": null,
          "logBase": 1,
          "max": null,
          "min": null,
          "show": false
        }
      ],
      "yaxis": {
        "align": false,
        "alignLevel": null
      }
    },
    {
      "collapsed": false,
      "datasource": null,
      "gridPos": {
        "h": 1,
        "w": 24,
        "x": 0,
        "y": 16
      },
      "id": 19,
      "panels": [],
      "repeat": null,
      "title": "Garbage Collection",
      "type": "row"
    },
    {
      "aliasColors": {},
      "bars": false,
      "dashLength": 10,
      "dashes": false,
      "datasource": "$datasource",
      "description": "Shows rate of execution for removals of blocks if their data is available as part of a block with a higher compaction level.",
      "fill": 10,
      "fillGradient": 0,
      "gridPos": {
        "h": 7,
        "w": 8,
        "x": 0,
        "y": 17
      },
      "hiddenSeries": false,
      "id": 5,
      "legend": {
        "avg": false,
        "current": false,
        "max": false,
        "min": false,
        "show": true,
        "total": false,
        "values": false
      },
      "lines": true,
      "linewidth": 0,
      "links": [],
      "nullPointMode": "null as zero",
      "options": {
        "dataLinks": []
      },
      "percentage": false,
      "pointradius": 5,
      "points": false,
      "renderer": "flot",
      "seriesOverrides": [],
      "spaceLength": 10,
      "stack": true,
      "steppedLine": false,
      "targets": [
        {
          "expr": "sum(rate(thanos_compact_garbage_collection_total{namespace=\"$namespace\",job=~\"$job\",pod=~\"$pod\"}[$interval])) by (job)",
          "format": "time_series",
          "interval": "",
          "intervalFactor": 2,
          "legendFormat": "garbage collection",
          "legendLink": null,
          "refId": "A",
          "step": 10
        }
      ],
      "thresholds": [],
      "timeFrom": null,
      "timeRegions": [],
      "timeShift": null,
      "title": "Rate",
      "tooltip": {
        "shared": true,
        "sort": 2,
        "value_type": "individual"
      },
      "type": "graph",
      "xaxis": {
        "buckets": null,
        "mode": "time",
        "name": null,
        "show": true,
        "values": []
      },
      "yaxes": [
        {
          "format": "short",
          "label": null,
          "logBase": 1,
          "max": null,
          "min": 0,
          "show": true
        },
        {
          "format": "short",
          "label": null,
          "logBase": 1,
          "max": null,
          "min": null,
          "show": false
        }
      ],
      "yaxis": {
        "align": false,
        "alignLevel": null
      }
    },
    {
      "aliasColors": {
        "error": "#E24D42"
      },
      "bars": false,
      "dashLength": 10,
      "dashes": false,
      "datasource": "$datasource",
      "description": "Shows ratio of errors compared to the total number of executed garbage collections.",
      "fill": 10,
      "fillGradient": 0,
      "gridPos": {
        "h": 7,
        "w": 8,
        "x": 8,
        "y": 17
      },
      "hiddenSeries": false,
      "id": 6,
      "legend": {
        "avg": false,
        "current": false,
        "max": false,
        "min": false,
        "show": true,
        "total": false,
        "values": false
      },
      "lines": true,
      "linewidth": 0,
      "links": [],
      "nullPointMode": "null as zero",
      "options": {
        "dataLinks": []
      },
      "percentage": false,
      "pointradius": 5,
      "points": false,
      "renderer": "flot",
      "seriesOverrides": [],
      "spaceLength": 10,
      "stack": true,
      "steppedLine": false,
      "targets": [
        {
          "expr": "sum(rate(thanos_compact_garbage_collection_failures_total{namespace=\"$namespace\",job=~\"$job\",pod=~\"$pod\"}[$interval])) / sum(rate(thanos_compact_garbage_collection_total{namespace=\"$namespace\",job=~\"$job\",pod=~\"$pod\"}[$interval]))",
          "format": "time_series",
          "interval": "",
          "intervalFactor": 2,
          "legendFormat": "error",
          "refId": "A",
          "step": 10
        }
      ],
      "thresholds": [],
      "timeFrom": null,
      "timeRegions": [],
      "timeShift": null,
      "title": "Errors",
      "tooltip": {
        "shared": true,
        "sort": 2,
        "value_type": "individual"
      },
      "type": "graph",
      "xaxis": {
        "buckets": null,
        "mode": "time",
        "name": null,
        "show": true,
        "values": []
      },
      "yaxes": [
        {
          "format": "percentunit",
          "label": null,
          "logBase": 1,
          "max": null,
          "min": 0,
          "show": true
        },
        {
          "format": "short",
          "label": null,
          "logBase": 1,
          "max": null,
          "min": null,
          "show": false
        }
      ],
      "yaxis": {
        "align": false,
        "alignLevel": null
      }
    },
    {
      "aliasColors": {},
      "bars": false,
      "dashLength": 10,
      "dashes": false,
      "datasource": "$datasource",
      "description": "Shows how long has it taken to execute garbage collection in quantiles.",
      "fill": 1,
      "fillGradient": 0,
      "gridPos": {
        "h": 7,
        "w": 8,
        "x": 16,
        "y": 17
      },
      "hiddenSeries": false,
      "id": 7,
      "legend": {
        "avg": false,
        "current": false,
        "max": false,
        "min": false,
        "show": true,
        "total": false,
        "values": false
      },
      "lines": true,
      "linewidth": 1,
      "links": [],
      "nullPointMode": "null as zero",
      "options": {
        "dataLinks": []
      },
      "percentage": false,
      "pointradius": 5,
      "points": false,
      "renderer": "flot",
      "seriesOverrides": [],
      "spaceLength": 10,
      "stack": false,
      "steppedLine": false,
      "targets": [
        {
          "expr": "histogram_quantile(0.99, sum(rate(thanos_compact_garbage_collection_duration_seconds_bucket{namespace=\"$namespace\",job=~\"$job\",pod=~\"$pod\"}[$interval])) by (le)) * 1",
          "format": "time_series",
          "interval": "",
          "intervalFactor": 2,
          "legendFormat": "P99",
          "refId": "A",
          "step": 10
        },
        {
          "expr": "sum(rate(thanos_compact_garbage_collection_duration_seconds_sum{namespace=\"$namespace\",job=~\"$job\",pod=~\"$pod\"}[$interval])) * 1 / sum(rate(thanos_compact_garbage_collection_duration_seconds_count{namespace=\"$namespace\",job=~\"$job\",pod=~\"$pod\"}[$interval]))",
          "format": "time_series",
          "interval": "",
          "intervalFactor": 2,
          "legendFormat": "mean",
          "refId": "B",
          "step": 10
        },
        {
          "expr": "histogram_quantile(0.50, sum(rate(thanos_compact_garbage_collection_duration_seconds_bucket{namespace=\"$namespace\",job=~\"$job\"}[$interval])) by (le)) * 1",
          "format": "time_series",
          "interval": "",
          "intervalFactor": 2,
          "legendFormat": "P50",
          "refId": "C",
          "step": 10
        }
      ],
      "thresholds": [],
      "timeFrom": null,
      "timeRegions": [],
      "timeShift": null,
      "title": "Duration",
      "tooltip": {
        "shared": true,
        "sort": 2,
        "value_type": "individual"
      },
      "type": "graph",
      "xaxis": {
        "buckets": null,
        "mode": "time",
        "name": null,
        "show": true,
        "values": []
      },
      "yaxes": [
        {
          "format": "s",
          "label": null,
          "logBase": 1,
          "max": null,
          "min": 0,
          "show": true
        },
        {
          "format": "short",
          "label": null,
          "logBase": 1,
          "max": null,
          "min": null,
          "show": false
        }
      ],
      "yaxis": {
        "align": false,
        "alignLevel": null
      }
    },
    {
      "collapsed": false,
      "datasource": null,
      "gridPos": {
        "h": 1,
        "w": 24,
        "x": 0,
        "y": 24
      },
      "id": 20,
      "panels": [],
      "repeat": null,
      "title": "Sync Meta",
      "type": "row"
    },
    {
      "aliasColors": {},
      "bars": false,
      "dashLength": 10,
      "dashes": false,
      "datasource": "$datasource",
      "description": "Shows rate of execution for all meta files from blocks in the bucket into the memory.",
      "fill": 10,
      "fillGradient": 0,
      "gridPos": {
        "h": 7,
        "w": 8,
        "x": 0,
        "y": 25
      },
      "hiddenSeries": false,
      "id": 8,
      "legend": {
        "avg": false,
        "current": false,
        "max": false,
        "min": false,
        "show": true,
        "total": false,
        "values": false
      },
      "lines": true,
      "linewidth": 0,
      "links": [],
      "nullPointMode": "null as zero",
      "options": {
        "dataLinks": []
      },
      "percentage": false,
      "pointradius": 5,
      "points": false,
      "renderer": "flot",
      "seriesOverrides": [],
      "spaceLength": 10,
      "stack": true,
      "steppedLine": false,
      "targets": [
        {
          "expr": "sum(rate(thanos_blocks_meta_syncs_total{namespace=\"$namespace\",job=~\"$job\",pod=~\"$pod\"}[$interval])) by (job)",
          "format": "time_series",
          "interval": "",
          "intervalFactor": 2,
          "legendFormat": "sync",
          "legendLink": null,
          "refId": "A",
          "step": 10
        }
      ],
      "thresholds": [],
      "timeFrom": null,
      "timeRegions": [],
      "timeShift": null,
      "title": "Rate",
      "tooltip": {
        "shared": true,
        "sort": 2,
        "value_type": "individual"
      },
      "type": "graph",
      "xaxis": {
        "buckets": null,
        "mode": "time",
        "name": null,
        "show": true,
        "values": []
      },
      "yaxes": [
        {
          "format": "short",
          "label": null,
          "logBase": 1,
          "max": null,
          "min": 0,
          "show": true
        },
        {
          "format": "short",
          "label": null,
          "logBase": 1,
          "max": null,
          "min": null,
          "show": false
        }
      ],
      "yaxis": {
        "align": false,
        "alignLevel": null
      }
    },
    {
      "aliasColors": {
        "error": "#E24D42"
      },
      "bars": false,
      "dashLength": 10,
      "dashes": false,
      "datasource": "$datasource",
      "description": "Shows ratio of errors compared to the total number of executed meta file sync.",
      "fill": 10,
      "fillGradient": 0,
      "gridPos": {
        "h": 7,
        "w": 8,
        "x": 8,
        "y": 25
      },
      "hiddenSeries": false,
      "id": 9,
      "legend": {
        "avg": false,
        "current": false,
        "max": false,
        "min": false,
        "show": true,
        "total": false,
        "values": false
      },
      "lines": true,
      "linewidth": 0,
      "links": [],
      "nullPointMode": "null as zero",
      "options": {
        "dataLinks": []
      },
      "percentage": false,
      "pointradius": 5,
      "points": false,
      "renderer": "flot",
      "seriesOverrides": [],
      "spaceLength": 10,
      "stack": true,
      "steppedLine": false,
      "targets": [
        {
          "expr": "sum(rate(thanos_blocks_meta_sync_failures_total{namespace=\"$namespace\",job=~\"$job\",pod=~\"$pod\"}[$interval])) / sum(rate(thanos_blocks_meta_syncs_total{namespace=\"$namespace\",job=~\"$job\",pod=~\"$pod\"}[$interval]))",
          "format": "time_series",
          "interval": "",
          "intervalFactor": 2,
          "legendFormat": "error",
          "refId": "A",
          "step": 10
        }
      ],
      "thresholds": [],
      "timeFrom": null,
      "timeRegions": [],
      "timeShift": null,
      "title": "Errors",
      "tooltip": {
        "shared": true,
        "sort": 2,
        "value_type": "individual"
      },
      "type": "graph",
      "xaxis": {
        "buckets": null,
        "mode": "time",
        "name": null,
        "show": true,
        "values": []
      },
      "yaxes": [
        {
          "format": "percentunit",
          "label": null,
          "logBase": 1,
          "max": null,
          "min": 0,
          "show": true
        },
        {
          "format": "short",
          "label": null,
          "logBase": 1,
          "max": null,
          "min": null,
          "show": false
        }
      ],
      "yaxis": {
        "align": false,
        "alignLevel": null
      }
    },
    {
      "aliasColors": {},
      "bars": false,
      "dashLength": 10,
      "dashes": false,
      "datasource": "$datasource",
      "description": "Shows how long has it taken to execute meta file sync, in quantiles.",
      "fill": 1,
      "fillGradient": 0,
      "gridPos": {
        "h": 7,
        "w": 8,
        "x": 16,
        "y": 25
      },
      "hiddenSeries": false,
      "id": 10,
      "legend": {
        "avg": false,
        "current": false,
        "max": false,
        "min": false,
        "show": true,
        "total": false,
        "values": false
      },
      "lines": true,
      "linewidth": 1,
      "links": [],
      "nullPointMode": "null as zero",
      "options": {
        "dataLinks": []
      },
      "percentage": false,
      "pointradius": 5,
      "points": false,
      "renderer": "flot",
      "seriesOverrides": [],
      "spaceLength": 10,
      "stack": false,
      "steppedLine": false,
      "targets": [
        {
          "expr": "histogram_quantile(0.99, sum(rate(thanos_blocks_meta_sync_duration_seconds_bucket{namespace=\"$namespace\",job=~\"$job\",pod=~\"$pod\"}[$interval])) by (le)) * 1",
          "format": "time_series",
          "interval": "",
          "intervalFactor": 2,
          "legendFormat": "P99",
          "refId": "A",
          "step": 10
        },
        {
          "expr": "sum(rate(thanos_blocks_meta_sync_duration_seconds_sum{namespace=\"$namespace\",job=~\"$job\",pod=~\"$pod\"}[$interval])) * 1 / sum(rate(thanos_blocks_meta_sync_duration_seconds_count{namespace=\"$namespace\",job=~\"$job\",pod=~\"$pod\"}[$interval]))",
          "format": "time_series",
          "interval": "",
          "intervalFactor": 2,
          "legendFormat": "mean",
          "refId": "B",
          "step": 10
        },
        {
          "expr": "histogram_quantile(0.50, sum(rate(thanos_blocks_meta_sync_duration_seconds_bucket{namespace=\"$namespace\",job=~\"$job\",pod=~\"$pod\"}[$interval])) by (le)) * 1",
          "format": "time_series",
          "interval": "",
          "intervalFactor": 2,
          "legendFormat": "P50",
          "refId": "C",
          "step": 10
        }
      ],
      "thresholds": [],
      "timeFrom": null,
      "timeRegions": [],
      "timeShift": null,
      "title": "Duration",
      "tooltip": {
        "shared": true,
        "sort": 2,
        "value_type": "individual"
      },
      "type": "graph",
      "xaxis": {
        "buckets": null,
        "mode": "time",
        "name": null,
        "show": true,
        "values": []
      },
      "yaxes": [
        {
          "format": "s",
          "label": null,
          "logBase": 1,
          "max": null,
          "min": 0,
          "show": true
        },
        {
          "format": "short",
          "label": null,
          "logBase": 1,
          "max": null,
          "min": null,
          "show": false
        }
      ],
      "yaxis": {
        "align": false,
        "alignLevel": null
      }
    },
    {
      "collapsed": false,
      "datasource": null,
      "gridPos": {
        "h": 1,
        "w": 24,
        "x": 0,
        "y": 32
      },
      "id": 21,
      "panels": [],
      "repeat": null,
      "title": "Object Store Operations",
      "type": "row"
    },
    {
      "aliasColors": {},
      "bars": false,
      "dashLength": 10,
      "dashes": false,
      "datasource": "$datasource",
      "description": "Shows rate of execution for operations against the bucket.",
      "fill": 10,
      "fillGradient": 0,
      "gridPos": {
        "h": 7,
        "w": 8,
        "x": 0,
        "y": 33
      },
      "hiddenSeries": false,
      "id": 11,
      "legend": {
        "avg": false,
        "current": false,
        "max": false,
        "min": false,
        "show": true,
        "total": false,
        "values": false
      },
      "lines": true,
      "linewidth": 0,
      "links": [],
      "nullPointMode": "null as zero",
      "options": {
        "dataLinks": []
      },
      "percentage": false,
      "pointradius": 5,
      "points": false,
      "renderer": "flot",
      "seriesOverrides": [],
      "spaceLength": 10,
      "stack": true,
      "steppedLine": false,
      "targets": [
        {
          "expr": "sum(rate(thanos_objstore_bucket_operations_total{namespace=\"$namespace\",job=~\"$job\",pod=~\"$pod\"}[$interval])) by (operation)",
          "format": "time_series",
          "interval": "",
          "intervalFactor": 2,
          "legendFormat": "{{operation}}",
          "legendLink": null,
          "refId": "A",
          "step": 10
        }
      ],
      "thresholds": [],
      "timeFrom": null,
      "timeRegions": [],
      "timeShift": null,
      "title": "Rate",
      "tooltip": {
        "shared": true,
        "sort": 2,
        "value_type": "individual"
      },
      "type": "graph",
      "xaxis": {
        "buckets": null,
        "mode": "time",
        "name": null,
        "show": true,
        "values": []
      },
      "yaxes": [
        {
          "format": "short",
          "label": null,
          "logBase": 1,
          "max": null,
          "min": 0,
          "show": true
        },
        {
          "format": "short",
          "label": null,
          "logBase": 1,
          "max": null,
          "min": null,
          "show": false
        }
      ],
      "yaxis": {
        "align": false,
        "alignLevel": null
      }
    },
    {
      "aliasColors": {
        "error": "#E24D42"
      },
      "bars": false,
      "dashLength": 10,
      "dashes": false,
      "datasource": "$datasource",
      "description": "Shows ratio of errors compared to the total number of executed operations against the bucket.",
      "fill": 10,
      "fillGradient": 0,
      "gridPos": {
        "h": 7,
        "w": 8,
        "x": 8,
        "y": 33
      },
      "hiddenSeries": false,
      "id": 12,
      "legend": {
        "avg": false,
        "current": false,
        "max": false,
        "min": false,
        "show": true,
        "total": false,
        "values": false
      },
      "lines": true,
      "linewidth": 0,
      "links": [],
      "nullPointMode": "null as zero",
      "options": {
        "dataLinks": []
      },
      "percentage": false,
      "pointradius": 5,
      "points": false,
      "renderer": "flot",
      "seriesOverrides": [],
      "spaceLength": 10,
      "stack": true,
      "steppedLine": false,
      "targets": [
        {
          "expr": "sum(rate(thanos_objstore_bucket_operation_failures_total{namespace=\"$namespace\",job=~\"$job\",pod=~\"$pod\"}[$interval])) / sum(rate(thanos_objstore_bucket_operations_total{namespace=\"$namespace\",job=~\"$job\",pod=~\"$pod\"}[$interval]))",
          "format": "time_series",
          "interval": "",
          "intervalFactor": 2,
          "legendFormat": "error",
          "refId": "A",
          "step": 10
        }
      ],
      "thresholds": [],
      "timeFrom": null,
      "timeRegions": [],
      "timeShift": null,
      "title": "Errors",
      "tooltip": {
        "shared": true,
        "sort": 2,
        "value_type": "individual"
      },
      "type": "graph",
      "xaxis": {
        "buckets": null,
        "mode": "time",
        "name": null,
        "show": true,
        "values": []
      },
      "yaxes": [
        {
          "format": "percentunit",
          "label": null,
          "logBase": 1,
          "max": null,
          "min": 0,
          "show": true
        },
        {
          "format": "short",
          "label": null,
          "logBase": 1,
          "max": null,
          "min": null,
          "show": false
        }
      ],
      "yaxis": {
        "align": false,
        "alignLevel": null
      }
    },
    {
      "aliasColors": {},
      "bars": false,
      "dashLength": 10,
      "dashes": false,
      "datasource": "$datasource",
      "description": "Shows how long has it taken to execute operations against the bucket, in quantiles.",
      "fill": 1,
      "fillGradient": 0,
      "gridPos": {
        "h": 7,
        "w": 8,
        "x": 16,
        "y": 33
      },
      "hiddenSeries": false,
      "id": 13,
      "legend": {
        "avg": false,
        "current": false,
        "max": false,
        "min": false,
        "show": true,
        "total": false,
        "values": false
      },
      "lines": true,
      "linewidth": 1,
      "links": [],
      "nullPointMode": "null as zero",
      "options": {
        "dataLinks": []
      },
      "percentage": false,
      "pointradius": 5,
      "points": false,
      "renderer": "flot",
      "seriesOverrides": [],
      "spaceLength": 10,
      "stack": false,
      "steppedLine": false,
      "targets": [
        {
          "expr": "histogram_quantile(0.99, sum(rate(thanos_objstore_bucket_operation_duration_seconds_bucket{namespace=\"$namespace\",job=~\"$job\",pod=~\"$pod\"}[$interval])) by (job, le)) * 1",
          "format": "time_series",
          "interval": "",
          "intervalFactor": 2,
          "legendFormat": "P99",
          "refId": "A",
          "step": 10
        },
        {
          "expr": "sum(rate(thanos_objstore_bucket_operation_duration_seconds_sum{namespace=\"$namespace\",job=~\"$job\",pod=~\"$pod\"}[$interval])) by (job) * 1 / sum(rate(thanos_objstore_bucket_operation_duration_seconds_count{namespace=\"$namespace\",job=~\"$job\",pod=~\"$pod\"}[$interval])) by (job)",
          "format": "time_series",
          "interval": "",
          "intervalFactor": 2,
          "legendFormat": "mean",
          "refId": "B",
          "step": 10
        },
        {
          "expr": "histogram_quantile(0.50, sum(rate(thanos_objstore_bucket_operation_duration_seconds_bucket{namespace=\"$namespace\",job=~\"$job\",pod=~\"$pod\"}[$interval])) by (job, le)) * 1",
          "format": "time_series",
          "interval": "",
          "intervalFactor": 2,
          "legendFormat": "P50",
          "refId": "C",
          "step": 10
        }
      ],
      "thresholds": [],
      "timeFrom": null,
      "timeRegions": [],
      "timeShift": null,
      "title": "Duration",
      "tooltip": {
        "shared": true,
        "sort": 2,
        "value_type": "individual"
      },
      "type": "graph",
      "xaxis": {
        "buckets": null,
        "mode": "time",
        "name": null,
        "show": true,
        "values": []
      },
      "yaxes": [
        {
          "format": "s",
          "label": null,
          "logBase": 1,
          "max": null,
          "min": 0,
          "show": true
        },
        {
          "format": "short",
          "label": null,
          "logBase": 1,
          "max": null,
          "min": null,
          "show": false
        }
      ],
      "yaxis": {
        "align": false,
        "alignLevel": null
      }
    },
    {
      "collapsed": true,
      "datasource": null,
      "gridPos": {
        "h": 1,
        "w": 24,
        "x": 0,
        "y": 40
      },
      "id": 22,
      "panels": [
        {
          "aliasColors": {},
          "bars": false,
          "dashLength": 10,
          "dashes": false,
          "datasource": "$datasource",
          "fill": 1,
          "fillGradient": 0,
          "gridPos": {
            "h": 7,
            "w": 8,
            "x": 0,
            "y": 41
          },
          "hiddenSeries": false,
          "id": 14,
          "legend": {
            "avg": false,
            "current": false,
            "max": false,
            "min": false,
            "show": true,
            "total": false,
            "values": false
          },
          "lines": true,
          "linewidth": 1,
          "links": [],
          "nullPointMode": "null as zero",
          "options": {
            "dataLinks": []
          },
          "percentage": false,
          "pointradius": 5,
          "points": false,
          "renderer": "flot",
          "seriesOverrides": [],
          "spaceLength": 10,
          "stack": false,
          "steppedLine": false,
          "targets": [
            {
              "expr": "go_memstats_alloc_bytes{namespace=\"$namespace\",job=~\"$job\",pod=~\"$pod\"}",
              "format": "time_series",
              "interval": "",
              "intervalFactor": 2,
              "legendFormat": "alloc all - {{namespace}}",
              "legendLink": null,
              "refId": "A",
              "step": 10
            },
            {
              "expr": "go_memstats_heap_alloc_bytes{namespace=\"$namespace\",job=~\"$job\",pod=~\"$pod\"}",
              "format": "time_series",
              "interval": "",
              "intervalFactor": 2,
              "legendFormat": "alloc heap - {{namespace}}",
              "legendLink": null,
              "refId": "B",
              "step": 10
            },
            {
              "expr": "rate(go_memstats_alloc_bytes_total{namespace=\"$namespace\",job=~\"$job\",pod=~\"$pod\"}[30s])",
              "format": "time_series",
              "interval": "",
              "intervalFactor": 2,
              "legendFormat": "alloc rate all - {{namespace}}",
              "legendLink": null,
              "refId": "C",
              "step": 10
            },
            {
              "expr": "rate(go_memstats_heap_alloc_bytes{namespace=\"$namespace\",job=~\"$job\",pod=~\"$pod\"}[30s])",
              "format": "time_series",
              "interval": "",
              "intervalFactor": 2,
              "legendFormat": "alloc rate heap - {{namespace}}",
              "legendLink": null,
              "refId": "D",
              "step": 10
            },
            {
              "expr": "go_memstats_stack_inuse_bytes{namespace=\"$namespace\",job=~\"$job\",pod=~\"$pod\"}",
              "format": "time_series",
              "interval": "",
              "intervalFactor": 2,
              "legendFormat": "inuse stack - {{namespace}}",
              "legendLink": null,
              "refId": "E",
              "step": 10
            },
            {
              "expr": "go_memstats_heap_inuse_bytes{namespace=\"$namespace\",job=~\"$job\",pod=~\"$pod\"}",
              "format": "time_series",
              "interval": "",
              "intervalFactor": 2,
              "legendFormat": "inuse heap - {{namespace}}",
              "legendLink": null,
              "refId": "F",
              "step": 10
            }
          ],
          "thresholds": [],
          "timeFrom": null,
          "timeRegions": [],
          "timeShift": null,
          "title": "Memory Used",
          "tooltip": {
            "shared": true,
            "sort": 2,
            "value_type": "individual"
          },
          "type": "graph",
          "xaxis": {
            "buckets": null,
            "mode": "time",
            "name": null,
            "show": true,
            "values": []
          },
          "yaxes": [
            {
              "format": "bytes",
              "label": null,
              "logBase": 1,
              "max": null,
              "min": 0,
              "show": true
            },
            {
              "format": "short",
              "label": null,
              "logBase": 1,
              "max": null,
              "min": null,
              "show": false
            }
          ],
          "yaxis": {
            "align": false,
            "alignLevel": null
          }
        },
        {
          "aliasColors": {},
          "bars": false,
          "dashLength": 10,
          "dashes": false,
          "datasource": "$datasource",
          "fill": 1,
          "fillGradient": 0,
          "gridPos": {
            "h": 7,
            "w": 8,
            "x": 8,
            "y": 41
          },
          "hiddenSeries": false,
          "id": 15,
          "legend": {
            "avg": false,
            "current": false,
            "max": false,
            "min": false,
            "show": true,
            "total": false,
            "values": false
          },
          "lines": true,
          "linewidth": 1,
          "links": [],
          "nullPointMode": "null as zero",
          "options": {
            "dataLinks": []
          },
          "percentage": false,
          "pointradius": 5,
          "points": false,
          "renderer": "flot",
          "seriesOverrides": [],
          "spaceLength": 10,
          "stack": false,
          "steppedLine": false,
          "targets": [
            {
              "expr": "go_goroutines{namespace=\"$namespace\",job=~\"$job\",pod=~\"$pod\"}",
              "format": "time_series",
              "interval": "",
              "intervalFactor": 2,
              "legendFormat": "{{pod}}",
              "legendLink": null,
              "refId": "A",
              "step": 10
            }
          ],
          "thresholds": [],
          "timeFrom": null,
          "timeRegions": [],
          "timeShift": null,
          "title": "Goroutines",
          "tooltip": {
            "shared": true,
            "sort": 2,
            "value_type": "individual"
          },
          "type": "graph",
          "xaxis": {
            "buckets": null,
            "mode": "time",
            "name": null,
            "show": true,
            "values": []
          },
          "yaxes": [
            {
              "format": "short",
              "label": null,
              "logBase": 1,
              "max": null,
              "min": 0,
              "show": true
            },
            {
              "format": "short",
              "label": null,
              "logBase": 1,
              "max": null,
              "min": null,
              "show": false
            }
          ],
          "yaxis": {
            "align": false,
            "alignLevel": null
          }
        },
        {
          "aliasColors": {},
          "bars": false,
          "dashLength": 10,
          "dashes": false,
          "datasource": "$datasource",
          "fill": 1,
          "fillGradient": 0,
          "gridPos": {
            "h": 7,
            "w": 8,
            "x": 16,
            "y": 41
          },
          "hiddenSeries": false,
          "id": 16,
          "legend": {
            "avg": false,
            "current": false,
            "max": false,
            "min": false,
            "show": true,
            "total": false,
            "values": false
          },
          "lines": true,
          "linewidth": 1,
          "links": [],
          "nullPointMode": "null as zero",
          "options": {
            "dataLinks": []
          },
          "percentage": false,
          "pointradius": 5,
          "points": false,
          "renderer": "flot",
          "seriesOverrides": [],
          "spaceLength": 10,
          "stack": false,
          "steppedLine": false,
          "targets": [
            {
              "expr": "go_gc_duration_seconds{namespace=\"$namespace\",job=~\"$job\",pod=~\"$pod\"}",
              "format": "time_series",
              "interval": "",
              "intervalFactor": 2,
              "legendFormat": "{{quantile}} - {{pod}}",
              "legendLink": null,
              "refId": "A",
              "step": 10
            }
          ],
          "thresholds": [],
          "timeFrom": null,
          "timeRegions": [],
          "timeShift": null,
          "title": "GC Time Quantiles",
          "tooltip": {
            "shared": true,
            "sort": 2,
            "value_type": "individual"
          },
          "type": "graph",
          "xaxis": {
            "buckets": null,
            "mode": "time",
            "name": null,
            "show": true,
            "values": []
          },
          "yaxes": [
            {
              "format": "short",
              "label": null,
              "logBase": 1,
              "max": null,
              "min": 0,
              "show": true
            },
            {
              "format": "short",
              "label": null,
              "logBase": 1,
              "max": null,
              "min": null,
              "show": false
            }
          ],
          "yaxis": {
            "align": false,
            "alignLevel": null
          }
        }
      ],
      "repeat": null,
      "title": "Resources",
      "type": "row"
    }
  ],
  "refresh": "10s",
  "schemaVersion": 22,
  "style": "dark",
  "tags": [
    "monitoring",
    "thanos"
  ],
  "templating": {
    "list": [
      {
        "current": {
          "selected": false,
          "tags": [],
          "text": "thanos",
          "value": "thanos"
        },
        "hide": 0,
        "includeAll": false,
        "label": null,
        "multi": false,
        "name": "datasource",
        "options": [],
        "query": "prometheus",
        "refresh": 1,
        "regex": "",
        "skipUrlSync": false,
        "type": "datasource"
      },
      {
        "current": {
          "selected": false,
          "text": "monitoring",
          "value": "monitoring"
        },
        "hide": 2,
        "label": "namespace",
        "name": "namespace",
        "options": [
          {
            "selected": true,
            "text": "monitoring",
            "value": "monitoring"
          }
        ],
        "query": "monitoring",
        "skipUrlSync": false,
        "type": "constant"
      },
      {
        "current": {
          "selected": false,
          "text": "kubernetes-pods",
          "value": "kubernetes-pods"
        },
        "hide": 2,
        "label": "job",
        "name": "job",
        "options": [
          {
            "selected": true,
            "text": "kubernetes-pods",
            "value": "kubernetes-pods"
          }
        ],
        "query": "kubernetes-pods",
        "skipUrlSync": false,
        "type": "constant"
      },
      {
        "allValue": "thanos-compact.*",
        "current": {
          "selected": false,
          "text": "All",
          "value": "$__all"
        },
        "datasource": "$datasource",
        "definition": "label_values(kube_pod_info{namespace=\"$namespace\",created_by_name=~\"thanos-compact.*\"}, pod)",
        "hide": 0,
        "includeAll": true,
        "index": -1,
        "label": "pod",
        "multi": false,
        "name": "pod",
        "options": [],
        "query": "label_values(kube_pod_info{namespace=\"$namespace\",created_by_name=~\"thanos-compact.*\"}, pod)",
        "refresh": 1,
        "regex": "",
        "skipUrlSync": false,
        "sort": 2,
        "tagValuesQuery": "",
        "tags": [],
        "tagsQuery": "",
        "type": "query",
        "useTags": false
      },
      {
        "auto": true,
        "auto_count": 300,
        "auto_min": "10s",
        "current": {
          "selected": false,
          "text": "5m",
          "value": "5m"
        },
        "hide": 0,
        "label": "interval",
        "name": "interval",
        "options": [
          {
            "selected": false,
            "text": "auto",
            "value": "$__auto_interval_interval"
          },
          {
            "selected": true,
            "text": "5m",
            "value": "5m"
          },
          {
            "selected": false,
            "text": "10m",
            "value": "10m"
          },
          {
            "selected": false,
            "text": "30m",
            "value": "30m"
          },
          {
            "selected": false,
            "text": "1h",
            "value": "1h"
          },
          {
            "selected": false,
            "text": "6h",
            "value": "6h"
          },
          {
            "selected": false,
            "text": "12h",
            "value": "12h"
          }
        ],
        "query": "5m,10m,30m,1h,6h,12h",
        "refresh": 2,
        "skipUrlSync": false,
        "type": "interval"
      }
    ]
  },
  "time": {
    "from": "now-1h",
    "to": "now"
  },
  "timepicker": {
    "refresh_intervals": [
      "5s",
      "10s",
      "30s",
      "1m",
      "5m",
      "15m",
      "30m",
      "1h",
      "2h",
      "1d"
    ],
    "time_options": [
      "5m",
      "15m",
      "1h",
      "6h",
      "12h",
      "24h",
      "2d",
      "7d",
      "30d"
    ]
  },
  "timezone": "",
  "title": "Thanos - Compact",
  "uid": "thanos-compact",
  "variables": {
    "list": []
  },
  "version": 14
}
